{".class": "MypyFile", "_fullname": "core.models", "is_partial_stub_package": false, "is_stub": false, "names": {".class": "SymbolTable", "Atracao": {".class": "SymbolTableNode", "cross_ref": "atracoes.models.Atracao", "kind": "Gdef"}, "Avaliacao": {".class": "SymbolTableNode", "cross_ref": "avaliacoes.models.Avaliacao", "kind": "Gdef"}, "CASCADE": {".class": "SymbolTableNode", "cross_ref": "tkinter.constants.CASCADE", "kind": "Gdef"}, "Comentarios": {".class": "SymbolTableNode", "cross_ref": "comentarios.models.Comentarios", "kind": "Gdef"}, "DocIdentificacao": {".class": "SymbolTableNode", "kind": "Gdef", "node": {".class": "TypeInfo", "_promote": null, "abstract_attributes": [], "bases": ["builtins.object"], "declared_metaclass": null, "defn": {".class": "ClassDef", "fullname": "core.models.DocIdentificacao", "name": "DocIdentificacao", "type_vars": []}, "flags": ["fallback_to_any"], "fullname": "core.models.DocIdentificacao", "metaclass_type": null, "metadata": {}, "module_name": "core.models", "mro": ["core.models.DocIdentificacao", "builtins.object"], "names": {".class": "SymbolTable", "description": {".class": "SymbolTableNode", "kind": "Mdef", "node": {".class": "Var", "flags": ["is_initialized_in_class"], "fullname": "core.models.DocIdentificacao.description", "name": "description", "type": {".class": "AnyType", "missing_import_name": "core.models.models", "source_any": {".class": "AnyType", "missing_import_name": "core.models.models", "source_any": null, "type_of_any": 3}, "type_of_any": 7}}}}, "tuple_type": null, "type_vars": [], "typeddict_type": null}}, "Endereco": {".class": "SymbolTableNode", "cross_ref": "endereco.models.Endereco", "kind": "Gdef"}, "PontoTuristico": {".class": "SymbolTableNode", "kind": "Gdef", "node": {".class": "TypeInfo", "_promote": null, "abstract_attributes": [], "bases": ["builtins.object"], "declared_metaclass": null, "defn": {".class": "ClassDef", "fullname": "core.models.PontoTuristico", "name": "PontoTuristico", "type_vars": []}, "flags": ["fallback_to_any"], "fullname": "core.models.PontoTuristico", "metaclass_type": null, "metadata": {}, "module_name": "core.models", "mro": ["core.models.PontoTuristico", "builtins.object"], "names": {".class": "SymbolTable", "__str__": {".class": "SymbolTableNode", "kind": "Mdef", "node": {".class": "FuncDef", "arg_kinds": [0], "arg_names": ["self"], "flags": [], "fullname": "core.models.PontoTuristico.__str__", "name": "__str__", "type": null}}, "aprovado": {".class": "SymbolTableNode", "kind": "Mdef", "node": {".class": "Var", "flags": ["is_initialized_in_class"], "fullname": "core.models.PontoTuristico.aprovado", "name": "aprovado", "type": {".class": "AnyType", "missing_import_name": "core.models.models", "source_any": {".class": "AnyType", "missing_import_name": "core.models.models", "source_any": null, "type_of_any": 3}, "type_of_any": 7}}}, "atracoes": {".class": "SymbolTableNode", "kind": "Mdef", "node": {".class": "Var", "flags": ["is_initialized_in_class"], "fullname": "core.models.PontoTuristico.atracoes", "name": "atracoes", "type": {".class": "AnyType", "missing_import_name": "core.models.models", "source_any": {".class": "AnyType", "missing_import_name": "core.models.models", "source_any": null, "type_of_any": 3}, "type_of_any": 7}}}, "avaliacoes": {".class": "SymbolTableNode", "kind": "Mdef", "node": {".class": "Var", "flags": ["is_initialized_in_class"], "fullname": "core.models.PontoTuristico.avaliacoes", "name": "avaliacoes", "type": {".class": "AnyType", "missing_import_name": "core.models.models", "source_any": {".class": "AnyType", "missing_import_name": "core.models.models", "source_any": null, "type_of_any": 3}, "type_of_any": 7}}}, "comentarios": {".class": "SymbolTableNode", "kind": "Mdef", "node": {".class": "Var", "flags": ["is_initialized_in_class"], "fullname": "core.models.PontoTuristico.comentarios", "name": "comentarios", "type": {".class": "AnyType", "missing_import_name": "core.models.models", "source_any": {".class": "AnyType", "missing_import_name": "core.models.models", "source_any": null, "type_of_any": 3}, "type_of_any": 7}}}, "descricao": {".class": "SymbolTableNode", "kind": "Mdef", "node": {".class": "Var", "flags": ["is_initialized_in_class"], "fullname": "core.models.PontoTuristico.descricao", "name": "descricao", "type": {".class": "AnyType", "missing_import_name": "core.models.models", "source_any": {".class": "AnyType", "missing_import_name": "core.models.models", "source_any": null, "type_of_any": 3}, "type_of_any": 7}}}, "descricao_completa2": {".class": "SymbolTableNode", "kind": "Mdef", "node": {".class": "Decorator", "func": {".class": "FuncDef", "arg_kinds": [0], "arg_names": ["self"], "flags": ["is_property", "is_decorated"], "fullname": "core.models.PontoTuristico.descricao_completa2", "name": "descricao_completa2", "type": null}, "is_overload": false, "var": {".class": "Var", "flags": ["is_initialized_in_class", "is_property", "is_ready"], "fullname": null, "name": "descricao_completa2", "type": {".class": "CallableType", "arg_kinds": [0], "arg_names": ["self"], "arg_types": ["core.models.PontoTuristico"], "bound_args": [], "def_extras": {}, "fallback": "builtins.function", "implicit": true, "is_ellipsis_args": false, "name": "descricao_completa2 of PontoTuristico", "ret_type": {".class": "AnyType", "missing_import_name": null, "source_any": null, "type_of_any": 1}, "variables": []}}}}, "doc_identificacao": {".class": "SymbolTableNode", "kind": "Mdef", "node": {".class": "Var", "flags": ["is_initialized_in_class"], "fullname": "core.models.PontoTuristico.doc_identificacao", "name": "doc_identificacao", "type": {".class": "AnyType", "missing_import_name": "core.models.models", "source_any": {".class": "AnyType", "missing_import_name": "core.models.models", "source_any": null, "type_of_any": 3}, "type_of_any": 7}}}, "endereco": {".class": "SymbolTableNode", "kind": "Mdef", "node": {".class": "Var", "flags": ["is_initialized_in_class"], "fullname": "core.models.PontoTuristico.endereco", "name": "endereco", "type": {".class": "AnyType", "missing_import_name": "core.models.models", "source_any": {".class": "AnyType", "missing_import_name": "core.models.models", "source_any": null, "type_of_any": 3}, "type_of_any": 7}}}, "foto": {".class": "SymbolTableNode", "kind": "Mdef", "node": {".class": "Var", "flags": ["is_initialized_in_class"], "fullname": "core.models.PontoTuristico.foto", "name": "foto", "type": {".class": "AnyType", "missing_import_name": "core.models.models", "source_any": {".class": "AnyType", "missing_import_name": "core.models.models", "source_any": null, "type_of_any": 3}, "type_of_any": 7}}}, "nome": {".class": "SymbolTableNode", "kind": "Mdef", "node": {".class": "Var", "flags": ["is_initialized_in_class"], "fullname": "core.models.PontoTuristico.nome", "name": "nome", "type": {".class": "AnyType", "missing_import_name": "core.models.models", "source_any": {".class": "AnyType", "missing_import_name": "core.models.models", "source_any": null, "type_of_any": 3}, "type_of_any": 7}}}}, "tuple_type": null, "type_vars": [], "typeddict_type": null}}, "__doc__": {".class": "SymbolTableNode", "kind": "Gdef", "node": {".class": "Var", "flags": ["is_ready"], "fullname": "core.models.__doc__", "name": "__doc__", "type": "builtins.str"}}, "__file__": {".class": "SymbolTableNode", "kind": "Gdef", "node": {".class": "Var", "flags": ["is_ready"], "fullname": "core.models.__file__", "name": "__file__", "type": "builtins.str"}}, "__name__": {".class": "SymbolTableNode", "kind": "Gdef", "node": {".class": "Var", "flags": ["is_ready"], "fullname": "core.models.__name__", "name": "__name__", "type": "builtins.str"}}, "__package__": {".class": "SymbolTableNode", "kind": "Gdef", "node": {".class": "Var", "flags": ["is_ready"], "fullname": "core.models.__package__", "name": "__package__", "type": "builtins.str"}}, "models": {".class": "SymbolTableNode", "kind": "Gdef", "node": {".class": "Var", "flags": ["is_suppressed_import", "is_ready"], "fullname": "core.models.models", "name": "models", "type": {".class": "AnyType", "missing_import_name": "core.models.models", "source_any": null, "type_of_any": 3}}}, "upload": {".class": "SymbolTableNode", "kind": "Gdef", "node": {".class": "Var", "flags": ["is_suppressed_import", "is_ready"], "fullname": "core.models.upload", "name": "upload", "type": {".class": "AnyType", "missing_import_name": "core.models.upload", "source_any": null, "type_of_any": 3}}}}, "path": "c:\\Users\\atila\\Desktop\\code\\apppontoturistico\\core\\models.py"}